{
  "allowed_entities": [
    "discount", "charge", "customer", "subscription", "plan" , "service", "product"
  ],
  "allowed_entities_actions": {
    "create": ["customer", "subscription", "product"],
    "permanentchange": ["product"]
  },
  "allowed_entities_importype": {
    "manual_mapping": ["customer", "subscription", "product"],
    "predefined_mapping": ["discount", "charge", "product"]
  },
  "default_values_allowed_actions": {
    "create": ["customer", "subscription", "product"],
    "permanentchange": []
  },
  "predefined_values_allowed_actions": {
    "create": ["customer", "subscription", "product"],
    "permanentchange": []
  },
  "hidden_actions_fields": {
    "create": {
      "customer": [],
      "subscription": [],
      "product": ["effective_date"]
    },
    "permanentchange": {
      "customer": [],
      "subscription": [],
      "product": ["tariff_category", "key", "usage_type", "usage_type_value", "from"]
    }
  },
  "allowed_plays": [
    "product"
  ]
}
